juna/__init__.py
juna/hiscores.py
juna/types.py
juna/utils.py
juna-0.1.0.dist-info/WHEEL
juna-0.1.0.dist-info/METADATA
juna-0.1.0.dist-info/RECORD
