Metadata-Version: 2.1
Name: juna
Version: 0.1.0
Summary: runescape utilities for python
Author: Nico Hämäläinen
Author-email: selitys@protonmail.ch
Requires-Python: >=3.9,<4.0
Classifier: Programming Language :: Python :: 3
Classifier: Programming Language :: Python :: 3.9
Requires-Dist: pydantic (>=1.7.3,<2.0.0)
Requires-Dist: requests (>=2.25.1,<3.0.0)
